src/MetricsParser.py
src/QMGeneric.py
src/__init__.py
src/metrics_to_calculate.py
src/metrics_to_extract.py
src/parse_qc.py
src/utils.py
qc_parser-0.8.3.dist-info/LICENSE
qc_parser-0.8.3.dist-info/METADATA
qc_parser-0.8.3.dist-info/WHEEL
qc_parser-0.8.3.dist-info/entry_points.txt
qc_parser-0.8.3.dist-info/RECORD
