Metadata-Version: 2.1
Name: qc-parser
Version: 0.8.3
Summary: Parses outputs of different QC tools and unifies them for the SMaHT portal
Home-page: https://github.com/smaht-dac/qc-parser
License: MIT
Author: Alexander Veit
Author-email: alexander_veit@hms.harvard.edu
Requires-Python: >=3.8,<3.12
Classifier: License :: OSI Approved :: MIT License
Classifier: Natural Language :: English
Classifier: Operating System :: POSIX :: Linux
Classifier: Programming Language :: Python :: 3
Classifier: Programming Language :: Python :: 3.8
Classifier: Programming Language :: Python :: 3.9
Classifier: Programming Language :: Python :: 3.10
Classifier: Programming Language :: Python :: 3.11
Classifier: Programming Language :: Python :: 3
Classifier: Programming Language :: Python :: 3.10
Classifier: Programming Language :: Python :: 3.11
Classifier: Programming Language :: Python :: 3.8
Classifier: Programming Language :: Python :: 3.9
Requires-Dist: click (>=8.1.3,<9.0.0)
Project-URL: Repository, https://github.com/smaht-dac/qc-parser
